fastbuilder/__init__.py
fastbuilder/build.py
fastbuilder/frontend_template.py
fastbuilder/import_sys.py
fastbuilder/tools_.py
fastbuilder/transfer.py
fastbuilder-0.1.0.dist-info/LICENSE
fastbuilder-0.1.0.dist-info/METADATA
fastbuilder-0.1.0.dist-info/WHEEL
fastbuilder-0.1.0.dist-info/RECORD
